StreamOneSDK/__init__.py
StreamOneSDK/client.py
StreamOneSDK/exceptions.py
StreamOneSDK/v1/__init__.py
StreamOneSDK/v1/billing/__init__.py
StreamOneSDK/v1/billing/billing.py
StreamOneSDK/v1/customers/__init__.py
StreamOneSDK/v1/customers/customers.py
StreamOneSDK/v3/__init__.py
StreamOneSDK/v3/customers/__init__.py
StreamOneSDK/v3/customers/customers.py
StreamOneSDK/v3/orders/__init__.py
StreamOneSDK/v3/orders/orders.py
StreamOneSDK/v3/products/__init__.py
StreamOneSDK/v3/products/products.py
StreamOneSDK/v3/reports/__init__.py
StreamOneSDK/v3/reports/reports.py
StreamOneSDK/v3/subscriptions/__init__.py
StreamOneSDK/v3/subscriptions/subscriptions.py
streamonesdk-0.1.2.dist-info/METADATA
streamonesdk-0.1.2.dist-info/WHEEL
streamonesdk-0.1.2.dist-info/top_level.txt
streamonesdk-0.1.2.dist-info/RECORD
