Metadata-Version: 2.4
Name: StreamOneSDK
Version: 0.1.2
Requires-Dist: requests
Dynamic: requires-dist
